LICENSE
README.md
setup.cfg
setup.py
croqueta/__init__.py
croqueta/maps.py
croqueta/obj.py
croqueta/pd.py
croqueta/str.py
croqueta/viz.py
croqueta.egg-info/PKG-INFO
croqueta.egg-info/SOURCES.txt
croqueta.egg-info/dependency_links.txt
croqueta.egg-info/top_level.txt