Metadata-Version: 2.1
Name: croqueta
Version: 0.2.3
Summary: A bunch of utilities to code even faster.
Home-page: https://github.com/juanluisrto/croqueta
Author: juanluisrto
Author-email: juanluis.rto@gmail.com
Requires-Python: >=3.8
License-File: LICENSE
